micrograph_cleaner_em/__init__.py
micrograph_cleaner_em/cleanMics.py
micrograph_cleaner_em/cleanOneMic.py
micrograph_cleaner_em/cmdParser.py
micrograph_cleaner_em/config.py
micrograph_cleaner_em/filesManager.py
micrograph_cleaner_em/filterCoords.py
micrograph_cleaner_em/predictMask.py
micrograph_cleaner_em/preprocessMic.py
micrograph_cleaner_em/utils.py
micrograph_cleaner_em/tests/__init__.py
micrograph_cleaner_em/tests/testConfig.py
micrograph_cleaner_em/tests/test_commanLineFun.py
micrograph_cleaner_em/tests/test_getMatchingFiles.py
micrograph_cleaner_em/tests/test_maskPredictor.py
micrograph_cleaner_em/tests/data/inCoords/relion/Ucsf_stack_1142_DW_autopick.star
micrograph_cleaner_em/tests/data/masks/Ucsf_stack_1142_DW.mrc
micrograph_cleaner_em/tests/data/mics/Ucsf_stack_1142_DW.mrc
micrograph_cleaner_em-1.0.2.dist-info/licenses/LICENSE
micrograph_cleaner_em-1.0.2.dist-info/METADATA
micrograph_cleaner_em-1.0.2.dist-info/WHEEL
micrograph_cleaner_em-1.0.2.dist-info/entry_points.txt
micrograph_cleaner_em-1.0.2.dist-info/top_level.txt
micrograph_cleaner_em-1.0.2.dist-info/RECORD
