Metadata-Version: 2.4
Name: micrograph-cleaner-em
Version: 1.0.2
Summary: Deep-learning micrograph denoising/segmentation for cryo-EM (TF2/Keras3 rescue)
Home-page: https://github.com/rsanchezgarc/micrograph_cleaner_em
Author: Original authors + maintainers
License: MIT
Classifier: Programming Language :: Python :: 3
Classifier: Programming Language :: Python :: 3 :: Only
Classifier: License :: OSI Approved :: MIT License
Classifier: Operating System :: OS Independent
Classifier: Topic :: Scientific/Engineering :: Image Processing
Classifier: Topic :: Scientific/Engineering :: Artificial Intelligence
Requires-Python: >=3.9
License-File: LICENSE
Requires-Dist: setuptools_scm
Requires-Dist: tensorflow[and-cuda]>=2.16
Requires-Dist: keras>=3.2
Requires-Dist: numpy>=1.26
Requires-Dist: scipy>=1.10
Requires-Dist: h5py>=3.10
Requires-Dist: joblib>=1.4
Requires-Dist: pandas>=2.3
Requires-Dist: scikit-image>=0.22
Requires-Dist: opencv-python-headless>=4.8
Requires-Dist: pillow>=10.0
Requires-Dist: imageio>=2.31
Requires-Dist: mrcfile>=1.5
Requires-Dist: matplotlib>=3.8
Requires-Dist: tqdm>=4.66
Requires-Dist: click>=8.1
Requires-Dist: protobuf<6,>=3.20
Requires-Dist: pytest
Dynamic: author
Dynamic: classifier
Dynamic: description
Dynamic: description-content-type
Dynamic: home-page
Dynamic: license
Dynamic: license-file
Dynamic: requires-dist
Dynamic: requires-python
Dynamic: summary
